b3bovespa/__init__.py
b3bovespa/scrapper.py
b3bovespa/utils/__init__.py
b3bovespa/utils/constants.py
b3bovespa/utils/utils.py
B3Bovespa-0.1.1.dist-info/LICENSE.txt
B3Bovespa-0.1.1.dist-info/METADATA
B3Bovespa-0.1.1.dist-info/WHEEL
B3Bovespa-0.1.1.dist-info/top_level.txt
B3Bovespa-0.1.1.dist-info/RECORD
