Metadata-Version: 2.1
Name: B3Bovespa
Version: 0.1.1
Summary: Package for web-scrapping companies from B3Bovespa
Home-page: https://github.com/pedroprates/b3bovespa
Author: Pedro Prates
Author-email: phprates@me.com
License: MIT
Download-URL: https://pypi.org/project/b3bovespa/
Keywords: b3,bovespa,web,scrap,company,stock,market
Platform: UNKNOWN
Requires-Dist: selenium (>=3.141.0)
Requires-Dist: pandas (>=1.1.0)
Requires-Dist: tqdm (>=4.48.2)
